[
    {
        "nickname": "Unknown",
        "timestamp": "05/06/2025 17:42",
        "latitude": 42.32723942,
        "longitude": -83.28077153
    },
    {
        "nickname": "777",
        "timestamp": "05/06/2025 15:48",
        "latitude": 42.451077,
        "longitude": -83.193842
    },
    {
        "nickname": "OUT",
        "timestamp": "04/04/2025 03:26",
        "latitude": 42.45135,
        "longitude": -83.193878
    },
    {
        "nickname": "IC",
        "timestamp": "05/06/2025 17:41",
        "latitude": 42.27684978,
        "longitude": -83.28799678
    },
    {
        "nickname": "723",
        "timestamp": "05/06/2025 17:41",
        "latitude": 42.32466852,
        "longitude": -83.2977432
    },
    {
        "nickname": "770",
        "timestamp": "05/06/2025 17:42",
        "latitude": 42.3025933,
        "longitude": -83.25428822
    },
    {
        "nickname": "OUT",
        "timestamp": "03/24/2025 11:25",
        "latitude": 42.451128,
        "longitude": -83.19343
    },
    {
        "nickname": "747",
        "timestamp": "05/06/2025 17:42",
        "latitude": 42.44397707,
        "longitude": -83.2179322
    },
    {
        "nickname": "776",
        "timestamp": "05/06/2025 17:41",
        "latitude": 42.29772702,
        "longitude": -83.24511712
    },
    {
        "nickname": "717",
        "timestamp": "05/06/2025 17:41",
        "latitude": 42.34376533,
        "longitude": -83.27817165
    },
    {
        "nickname": "735",
        "timestamp": "05/06/2025 17:42",
        "latitude": 42.2838757,
        "longitude": -83.26085672
    },
    {
        "nickname": "729",
        "timestamp": "05/06/2025 17:41",
        "latitude": 42.31950388,
        "longitude": -83.26604508
    },
    {
        "nickname": "765",
        "timestamp": "05/06/2025 17:42",
        "latitude": 42.27605,
        "longitude": -83.25454068
    },
    {
        "nickname": "764",
        "timestamp": "05/06/2025 17:42",
        "latitude": 42.33982085,
        "longitude": -83.26737437
    },
    {
        "nickname": "752",
        "timestamp": "05/06/2025 17:41",
        "latitude": 42.31268417,
        "longitude": -83.26665147
    },
    {
        "nickname": "741",
        "timestamp": "05/06/2025 17:42",
        "latitude": 42.2788044,
        "longitude": -83.24285653
    },
    {
        "nickname": "759",
        "timestamp": "05/06/2025 17:41",
        "latitude": 42.32723102,
        "longitude": -83.30935913
    },
    {
        "nickname": "771",
        "timestamp": "05/06/2025 17:36",
        "latitude": 42.451127,
        "longitude": -83.193802
    }
]