[
    {
        "nickname": "BEAST",
        "timestamp": "04/11/2025 15:40",
        "latitude": 42.29280002,
        "longitude": -83.2123377
    },
    {
        "nickname": "759",
        "timestamp": "04/21/2025 06:05",
        "latitude": 42.451077,
        "longitude": -83.193842
    },
    {
        "nickname": "OUT",
        "timestamp": "04/04/2025 03:26",
        "latitude": 42.45135,
        "longitude": -83.193878
    },
    {
        "nickname": "723",
        "timestamp": "04/21/2025 14:09",
        "latitude": 42.42875988,
        "longitude": -83.21934547
    },
    {
        "nickname": "759",
        "timestamp": "04/21/2025 03:47",
        "latitude": 42.451042,
        "longitude": -83.193757
    },
    {
        "nickname": "764",
        "timestamp": "04/21/2025 14:09",
        "latitude": 42.30644565,
        "longitude": -83.24563392
    },
    {
        "nickname": "OUT",
        "timestamp": "03/24/2025 11:25",
        "latitude": 42.451128,
        "longitude": -83.19343
    },
    {
        "nickname": "729",
        "timestamp": "04/21/2025 05:47",
        "latitude": 42.451069,
        "longitude": -83.193856
    },
    {
        "nickname": "771",
        "timestamp": "04/21/2025 14:09",
        "latitude": 42.41134233,
        "longitude": -83.2188303
    },
    {
        "nickname": "741",
        "timestamp": "04/18/2025 14:58",
        "latitude": 42.35419318,
        "longitude": -83.27615542
    },
    {
        "nickname": "776",
        "timestamp": "04/21/2025 10:36",
        "latitude": 42.45112,
        "longitude": -83.193771
    },
    {
        "nickname": "771",
        "timestamp": "04/21/2025 07:39",
        "latitude": 42.45109,
        "longitude": -83.193904
    },
    {
        "nickname": "752",
        "timestamp": "04/21/2025 03:29",
        "latitude": 42.450943,
        "longitude": -83.193788
    },
    {
        "nickname": "764",
        "timestamp": "04/21/2025 14:09",
        "latitude": 42.33549245,
        "longitude": -83.2374178
    },
    {
        "nickname": "771",
        "timestamp": "04/21/2025 12:57",
        "latitude": 42.451049,
        "longitude": -83.193473
    },
    {
        "nickname": "771",
        "timestamp": "04/21/2025 02:07",
        "latitude": 42.451125,
        "longitude": -83.193836
    },
    {
        "nickname": "752",
        "timestamp": "04/21/2025 14:09",
        "latitude": 42.31880315,
        "longitude": -83.24859338
    },
    {
        "nickname": "771",
        "timestamp": "04/21/2025 06:43",
        "latitude": 42.451106,
        "longitude": -83.193772
    }
]