[
    {
        "nickname": "Unknown",
        "timestamp": "05/02/2025 17:44",
        "latitude": 42.30112885,
        "longitude": -83.23231218
    },
    {
        "nickname": "753",
        "timestamp": "04/11/2025 15:40",
        "latitude": 42.29280002,
        "longitude": -83.2123377
    },
    {
        "nickname": "777",
        "timestamp": "05/02/2025 15:16",
        "latitude": 42.451077,
        "longitude": -83.193842
    },
    {
        "nickname": "OUT",
        "timestamp": "04/04/2025 03:26",
        "latitude": 42.45135,
        "longitude": -83.193878
    },
    {
        "nickname": "IC",
        "timestamp": "05/02/2025 17:47",
        "latitude": 42.28166737,
        "longitude": -83.27626972
    },
    {
        "nickname": "723",
        "timestamp": "05/02/2025 17:46",
        "latitude": 42.31504367,
        "longitude": -83.30385265
    },
    {
        "nickname": "770",
        "timestamp": "05/02/2025 17:47",
        "latitude": 42.30154235,
        "longitude": -83.25989525
    },
    {
        "nickname": "OUT",
        "timestamp": "03/24/2025 11:25",
        "latitude": 42.451128,
        "longitude": -83.19343
    },
    {
        "nickname": "747",
        "timestamp": "05/02/2025 17:47",
        "latitude": 42.30034533,
        "longitude": -83.26794582
    },
    {
        "nickname": "776",
        "timestamp": "05/02/2025 17:47",
        "latitude": 42.3387321,
        "longitude": -83.23890015
    },
    {
        "nickname": "717",
        "timestamp": "05/02/2025 17:47",
        "latitude": 42.33410618,
        "longitude": -83.27883602
    },
    {
        "nickname": "735",
        "timestamp": "05/02/2025 17:46",
        "latitude": 42.28861535,
        "longitude": -83.26888407
    },
    {
        "nickname": "729",
        "timestamp": "05/02/2025 17:47",
        "latitude": 42.31847497,
        "longitude": -83.2695425
    },
    {
        "nickname": "765",
        "timestamp": "05/02/2025 17:46",
        "latitude": 42.27413833,
        "longitude": -83.25581215
    },
    {
        "nickname": "764",
        "timestamp": "05/02/2025 17:46",
        "latitude": 42.34122847,
        "longitude": -83.31069477
    },
    {
        "nickname": "752",
        "timestamp": "05/02/2025 17:46",
        "latitude": 42.30916472,
        "longitude": -83.27551847
    },
    {
        "nickname": "741",
        "timestamp": "05/02/2025 17:47",
        "latitude": 42.28006247,
        "longitude": -83.24009995
    },
    {
        "nickname": "759",
        "timestamp": "05/02/2025 17:47",
        "latitude": 42.28741595,
        "longitude": -83.21676853
    },
    {
        "nickname": "771",
        "timestamp": "05/02/2025 04:32",
        "latitude": 42.451127,
        "longitude": -83.193802
    }
]